{
    "postPage": {
        "id": "5b13da97-30d4-40a6-be55-d44e8c25520e",
        "post": {
            "id": "5b13da97-30d4-40a6-be55-d44e8c25520e",
            "title": "Deccan Herald; Living forests, shared futures - Srinivasulu",
            "excerpt": "A number of families still live in acute poverty within protected forests. In the Kali Tiger Reserve (KTR), 71 hamlets are home to nearly...",
            "firstPublishedDate": "2025-08-07T12:37:57.557Z",
            "lastPublishedDate": "2025-08-07T13:48:20.852Z",
            "url": {
                "base": "https://www.srinivasifs.com",
                "path": "/post/living-forests-shared-futures-srinivasulu"
            },
            "slug": "living-forests-shared-futures-srinivasulu",
            "featured": false,
            "pinned": false,
            "categoryIds": [
                "c9e08f3b-8b9e-4598-8b8f-83a7623cc7ee"
            ],
            "memberId": "f453f3b8-30e5-448e-80db-7da2150ab909",
            "hashtags": [],
            "commentingEnabled": true,
            "postCountInfo": {
                "comments": 0,
                "likes": 0,
                "views": 15
            },
            "minutesToRead": 1,
            "tagIds": [],
            "relatedPostIds": [],
            "pricingPlanIds": [],
            "language": "en",
            "metrics": {
                "comments": 0,
                "likes": 0,
                "views": 15,
                "totalRatings": 0,
                "averageRating": 0
            },
            "seoData": {
                "tags": [],
                "settings": {
                    "preventAutoRedirect": false,
                    "keywords": []
                }
            },
            "richContent": {
                "nodes": [
                    {
                        "type": "PARAGRAPH",
                        "id": "lrwnu380",
                        "nodes": [
                            {
                                "type": "TEXT",
                                "id": "",
                                "nodes": [],
                                "textData": {
                                    "text": "A number of families still live in acute poverty within protected forests. In the Kali Tiger Reserve (KTR), 71 hamlets are home to nearly 2,000 families; the Nagarhole National Park (NNP) has 34 hamlets with about 1,280 families; and the Biligir Rang...",
                                    "decorations": [
                                        {
                                            "type": "COLOR",
                                            "colorData": {
                                                "background": "rgb(255, 255, 255)",
                                                "foreground": "rgb(0, 0, 0)"
                                            }
                                        }
                                    ]
                                }
                            }
                        ],
                        "paragraphData": {}
                    },
                    {
                        "type": "IMAGE",
                        "id": "upoi5416",
                        "nodes": [],
                        "imageData": {
                            "containerData": {
                                "width": {
                                    "size": "CONTENT"
                                },
                                "alignment": "CENTER",
                                "textWrap": true
                            },
                            "image": {
                                "src": {
                                    "id": "f453f3_80a3b144917a4529b5113d074bc81ee8~mv2.jpeg"
                                },
                                "width": 312,
                                "height": 1198
                            }
                        }
                    },
                    {
                        "type": "PARAGRAPH",
                        "id": "74swz383",
                        "nodes": [],
                        "style": {},
                        "paragraphData": {
                            "textStyle": {
                                "textAlignment": "AUTO"
                            }
                        }
                    },
                    {
                        "type": "PARAGRAPH",
                        "id": "4c56r384",
                        "nodes": [
                            {
                                "type": "TEXT",
                                "id": "",
                                "nodes": [],
                                "textData": {
                                    "text": "Read more at: ",
                                    "decorations": [
                                        {
                                            "type": "COLOR",
                                            "colorData": {
                                                "background": "rgb(255, 255, 255)",
                                                "foreground": "rgb(0, 0, 0)"
                                            }
                                        }
                                    ]
                                }
                            },
                            {
                                "type": "TEXT",
                                "id": "",
                                "nodes": [],
                                "textData": {
                                    "text": "https://www.deccanherald.com/opinion/living-forests-shared-futures-3618237?utm_source=whatsapp&utm_medium=referral&utm_campaign=socialshare",
                                    "decorations": [
                                        {
                                            "type": "LINK",
                                            "linkData": {
                                                "link": {
                                                    "url": "https://www.deccanherald.com/opinion/living-forests-shared-futures-3618237?utm_source=whatsapp&utm_medium=referral&utm_campaign=socialshare",
                                                    "target": "BLANK",
                                                    "rel": {
                                                        "noreferrer": true
                                                    }
                                                }
                                            }
                                        },
                                        {
                                            "type": "UNDERLINE"
                                        }
                                    ]
                                }
                            }
                        ],
                        "paragraphData": {}
                    }
                ],
                "documentStyle": {}
            },
            "contentId": "6894a7fa790df6e1aa852c91",
            "mostRecentContributorId": "f453f3b8-30e5-448e-80db-7da2150ab909",
            "media": {
                "wixMedia": {
                    "image": {
                        "id": "f453f3_3b10871ede884173a0c1c70b2e3a264a~mv2.jpg",
                        "url": "https://static.wixstatic.com/media/f453f3_3b10871ede884173a0c1c70b2e3a264a~mv2.jpg",
                        "height": 251,
                        "width": 312,
                        "filename": "0331973c-31ce-4e84-9347-cd01c252f1de_edited.jpg"
                    }
                },
                "displayed": true,
                "custom": true
            },
            "translations": [],
            "customExcerpt": false,
            "internalId": "68949dd6ddea84be3de5deb7",
            "internalCategoryIds": [
                "6894a872361afb873d30f5d9"
            ],
            "internalRelatedPostIds": [],
            "isLiked": false,
            "isSubscribed": false,
            "owner": {
                "activityStatus": "UNKNOWN",
                "contactId": "47771a5e-8348-4d09-965b-5cc09012410f",
                "id": "f453f3b8-30e5-448e-80db-7da2150ab909",
                "image": {
                    "id": "",
                    "url": "https://graph.facebook.com/3191009841011756/picture?type=large",
                    "height": 0,
                    "width": 0
                },
                "name": "sriniforest",
                "privacyStatus": "UNKNOWN",
                "siteMemberId": "f453f3b8-30e5-448e-80db-7da2150ab909",
                "slug": "sriniforest",
                "status": "UNKNOWN",
                "isBlocked": false,
                "isOwner": false,
                "appStore": {
                    "14bcded7-0066-7c35-14d7-466cb3f09103": {
                        "permissions": {
                            "role": "writer"
                        }
                    }
                }
            },
            "preview": false
        },
        "blog": {
            "settings": {
                "ampEnabled": false,
                "allPostsFeedLabel": "All Posts",
                "comments": {
                    "enabled": true,
                    "anonymousEnabled": false,
                    "ratingsEnabled": false,
                    "ratingsMandatory": false
                },
                "revision": {
                    "low": 2,
                    "high": 0,
                    "unsigned": false
                },
                "blocksPostPage": false,
                "liveSiteEditingDeprecated": false,
                "useBlogLikeService": true,
                "allPosts": "All Posts"
            },
            "translations": {
                "en": "All Posts"
            },
            "blogSettingsV2": {
                "ampEnabled": false,
                "allPostsFeedLabel": "All Posts",
                "comments": {
                    "enabled": true,
                    "anonymousEnabled": false,
                    "ratingsEnabled": false,
                    "ratingsMandatory": false
                },
                "revision": {
                    "low": 2,
                    "high": 0,
                    "unsigned": false
                },
                "blocksPostPage": false,
                "liveSiteEditingDeprecated": false,
                "useBlogLikeService": true
            }
        },
        "categories": [
            {
                "id": "c9e08f3b-8b9e-4598-8b8f-83a7623cc7ee",
                "label": "KFD - Wildlife",
                "postCount": 2,
                "url": {
                    "base": "https://www.srinivasifs.com",
                    "path": "/blog/categories/kfd-wildlife-1"
                },
                "title": "",
                "displayPosition": 999,
                "language": "en",
                "slug": "kfd-wildlife-1",
                "seoData": {
                    "tags": []
                },
                "coverImage": {
                    "id": "f453f3_aca3d434c40c4d10b761d578c93bcade~mv2.png",
                    "url": "https://static.wixstatic.com/media/f453f3_aca3d434c40c4d10b761d578c93bcade~mv2.png",
                    "height": 1889,
                    "width": 2329
                },
                "translations": []
            }
        ],
        "tags": [],
        "relatedPosts": [
            {
                "id": "57287912-8405-43ec-8f1d-c5f02a6d8090",
                "internalId": "6894b980979ca91c7c3e1dec",
                "slug": "srinivasulu-indian-forest-service-ifs-to-the-tedxabbs-stage",
                "url": {
                    "base": "https://www.srinivasifs.com",
                    "path": "/post/srinivasulu-indian-forest-service-ifs-to-the-tedxabbs-stage"
                },
                "media": {
                    "wixMedia": {
                        "image": {
                            "id": "f453f3_616a34f4ef764e4985addafaac351bd9~mv2.jpg",
                            "url": "https://static.wixstatic.com/media/f453f3_616a34f4ef764e4985addafaac351bd9~mv2.jpg",
                            "height": 6048,
                            "width": 4032,
                            "filename": "NGD_0712.jpg"
                        }
                    },
                    "displayed": true,
                    "custom": false
                },
                "title": "Srinivasulu, IFS to the TEDxABBS stage.",
                "liked": false,
                "subscribed": false,
                "excerpt": "Srinivasulu, Indian Forest Service (IFS) to the TEDxABBS stage. He plays a pivotal role in Forest & Wildlife Conservation, policy making,..."
            }
        ],
        "appData": {
            "ampEnabled": false,
            "menuLabel": "All Posts",
            "language": "en",
            "postPageEnabled": true
        },
        "blogSettingsV2": {
            "ampEnabled": false,
            "allPostsFeedLabel": "All Posts",
            "comments": {
                "enabled": true,
                "anonymousEnabled": false,
                "ratingsEnabled": false,
                "ratingsMandatory": false
            },
            "revision": {
                "low": 2,
                "high": 0,
                "unsigned": false
            },
            "blocksPostPage": false,
            "liveSiteEditingDeprecated": false,
            "useBlogLikeService": true
        }
    }
}